ivsort
