Metadata-Version: 1.0
Name: ivsort
Version: 0.2
Summary: proper sorting of pointed Hebrew texts
Home-page: https://github.com/ninjaaron/ivsort
Author: Aaron Christianson
Author-email: ninjaaron@gmail.com
License: UNKNOWN
Keywords: Hebrew sorting niqqud vowels
Platform: UNKNOWN
